[
  {
    "original": "грамотная речь",
    "duplicate": "грамотность",
    "percent": 64,
    "id": 12
  },
  {
    "original": "грамотная речь",
    "duplicate": "грамотная устная и письменная речь",
    "percent": 100,
    "id": 125
  },
  {
    "original": "грамотная речь",
    "duplicate": "грамотная русская речь (устная и письменная)",
    "percent": 100,
    "id": 177
  },
  {
    "original": "грамотная речь",
    "duplicate": "грамотная речь, умение убеждать",
    "percent": 100,
    "id": 360
  },
  {
    "original": "грамотная речь",
    "duplicate": "грамотная речь, ответственность, исполнительность, интерес к профессии",
    "percent": 100,
    "id": 633
  },
  {
    "original": "грамотная речь",
    "duplicate": "грамотная письменная речь",
    "percent": 100,
    "id": 699
  },
  {
    "original": "грамотная речь",
    "duplicate": "грамотная речь и письмо",
    "percent": 100,
    "id": 1032
  },
  {
    "original": "грамотная речь",
    "duplicate": "грамотная устная речь",
    "percent": 100,
    "id": 1134
  },
  {
    "original": "грамотная речь",
    "duplicate": "работа в команде, грамотная речь, желание обучаться.",
    "percent": 100,
    "id": 1160
  },
  {
    "original": "грамотная речь",
    "duplicate": "обработка речи",
    "percent": 64,
    "id": 2628
  },
  {
    "original": "грамотная речь",
    "duplicate": "поставленная речь",
    "percent": 65,
    "id": 3365
  },
  {
    "original": "грамотная речь",
    "duplicate": "грамотная речь заключение договоров деловая коммуникация ведение переговоров поиск и привлечение",
    "percent": 100,
    "id": 3442
  },
  {
    "original": "грамотная речь",
    "duplicate": "грамотная устная речь, хорошо поставленный голос, необходимая дикция",
    "percent": 100,
    "id": 4373
  },
  {
    "original": "грамотная речь",
    "duplicate": "грамотно поставленная речь",
    "percent": 70,
    "id": 4955
  },
  {
    "original": "грамотная речь",
    "duplicate": "активная жизненная позиция; грамотная, правильная речь; уверенность в себе.",
    "percent": 100,
    "id": 4963
  }
]